androidtvmcp/__init__.py
androidtvmcp/__main__.py
androidtvmcp/cli.py
androidtvmcp/commands.py
androidtvmcp/device_manager.py
androidtvmcp/models.py
androidtvmcp/server.py
mseep_androidtvmcp-0.2.2.dist-info/METADATA
mseep_androidtvmcp-0.2.2.dist-info/WHEEL
mseep_androidtvmcp-0.2.2.dist-info/entry_points.txt
mseep_androidtvmcp-0.2.2.dist-info/licenses/LICENSE
mseep_androidtvmcp-0.2.2.dist-info/RECORD
